easypythonx/__init__.py
easypythonx/core.py
easypythonx-0.1.0.dist-info/METADATA
easypythonx-0.1.0.dist-info/WHEEL
easypythonx-0.1.0.dist-info/top_level.txt
easypythonx-0.1.0.dist-info/RECORD
