Metadata-Version: 2.4
Name: easypythonx
Version: 0.1.0
Summary: A simple wrapper around boto3, requests, urllib3, and pyinstaller for fast automation.
Author: Tristan
Author-email: likelikefootball@gmail.com
Classifier: Programming Language :: Python :: 3
Classifier: License :: OSI Approved :: MIT License
Classifier: Operating System :: OS Independent
Requires-Python: >=3.6
Requires-Dist: boto3
Requires-Dist: requests
Requires-Dist: urllib3
Requires-Dist: pyinstaller
Dynamic: author
Dynamic: author-email
Dynamic: classifier
Dynamic: description-content-type
Dynamic: requires-dist
Dynamic: requires-python
Dynamic: summary
